TupleLanguage/ColorGrading.py
TupleLanguage/Shell.py
TupleLanguage/SingleLineInterpreter.py
TupleLanguage/__init__.py
TupleLanguage/base.py
TupleLanguage-0.0.1.dist-info/METADATA
TupleLanguage-0.0.1.dist-info/WHEEL
TupleLanguage-0.0.1.dist-info/top_level.txt
TupleLanguage-0.0.1.dist-info/RECORD
